AUTHORS.md
CONTRIBUTING.md
LICENSE
MANIFEST.in
README.md
requirements.txt
setup.cfg
setup.py
anchor/__init__.py
anchor/bayesian.py
anchor/binning.py
anchor/infotheory.py
anchor/model.py
anchor/names.py
anchor/simulate.py
anchor/util.py
anchor/visualize.py
anchor_bio.egg-info/PKG-INFO
anchor_bio.egg-info/SOURCES.txt
anchor_bio.egg-info/dependency_links.txt
anchor_bio.egg-info/not-zip-safe
anchor_bio.egg-info/requires.txt
anchor_bio.egg-info/top_level.txt