Metadata-Version: 1.1
Name: anchor-bio
Version: 1.1.1
Summary: Anchor is a python package to estimate modality of splicing, percent methylated, any data that is normalized between 0 and 1
Home-page: https://github.com/YeoLab/anchor
Author: Olga Botvinnik
Author-email: olga.botvinnik@gmail.com
License: BSD
Keywords: anchor
Platform: UNKNOWN
Classifier: Intended Audience :: Developers
Classifier: License :: OSI Approved :: BSD License
Classifier: Natural Language :: English
Classifier: Programming Language :: Python :: 2
Classifier: Programming Language :: Python :: 2.7
Classifier: Programming Language :: Python :: 3
Classifier: Programming Language :: Python :: 3.4
Classifier: Programming Language :: Python :: 3.5
Classifier: Programming Language :: Python :: 3.6
